coilcraft/__init__.py
coilcraft/coilcraft_loss.py
coilcraft-1.0.dist-info/METADATA
coilcraft-1.0.dist-info/WHEEL
coilcraft-1.0.dist-info/top_level.txt
coilcraft-1.0.dist-info/RECORD
