Metadata-Version: 2.1
Name: coilcraft
Version: 1.0
Summary: coilcraft_loss
Home-page: 
Author: felix
Author-email: qiyu_sjtu@163.com
License: UNKNOWN
Platform: UNKNOWN
